DSPro/__init__.py
DSPro/List/CLinkedList.py
DSPro/List/CList.py
DSPro/List/__init__.py
DSPro-0.0.3.dist-info/LICENSE.txt
DSPro-0.0.3.dist-info/METADATA
DSPro-0.0.3.dist-info/WHEEL
DSPro-0.0.3.dist-info/top_level.txt
DSPro-0.0.3.dist-info/RECORD
